statick_tool/__init__.py
statick_tool/args.py
statick_tool/config.py
statick_tool/discovery_plugin.py
statick_tool/exceptions.py
statick_tool/issue.py
statick_tool/package.py
statick_tool/plugin_context.py
statick_tool/profile.py
statick_tool/reporting_plugin.py
statick_tool/resources.py
statick_tool/statick.py
statick_tool/statick_tool.py
statick_tool/timing.py
statick_tool/tool_plugin.py
statick_tool/plugins/__init__.py
statick_tool/plugins/discovery/__init__.py
statick_tool/plugins/discovery/c.py
statick_tool/plugins/discovery/cmake.py
statick_tool/plugins/discovery/groovy.py
statick_tool/plugins/discovery/java.py
statick_tool/plugins/discovery/maven.py
statick_tool/plugins/discovery/perl.py
statick_tool/plugins/discovery/python.py
statick_tool/plugins/discovery/ros.py
statick_tool/plugins/discovery/shell.py
statick_tool/plugins/discovery/xml.py
statick_tool/plugins/discovery/yaml.py
statick_tool/plugins/reporting/__init__.py
statick_tool/plugins/reporting/code_climate.py
statick_tool/plugins/reporting/do_nothing.py
statick_tool/plugins/reporting/json.py
statick_tool/plugins/reporting/print_to_console.py
statick_tool/plugins/reporting/write_jenkins_warnings_ng.py
statick_tool/plugins/tool/__init__.py
statick_tool/plugins/tool/bandit.py
statick_tool/plugins/tool/black.py
statick_tool/plugins/tool/catkin_lint.py
statick_tool/plugins/tool/cccc.py
statick_tool/plugins/tool/clang_format.py
statick_tool/plugins/tool/clang_format_parser.py
statick_tool/plugins/tool/clang_tidy.py
statick_tool/plugins/tool/cmakelint.py
statick_tool/plugins/tool/cppcheck.py
statick_tool/plugins/tool/cpplint.py
statick_tool/plugins/tool/do_nothing.py
statick_tool/plugins/tool/docformatter.py
statick_tool/plugins/tool/flawfinder.py
statick_tool/plugins/tool/groovylint.py
statick_tool/plugins/tool/isort.py
statick_tool/plugins/tool/lizard.py
statick_tool/plugins/tool/make.py
statick_tool/plugins/tool/mypy.py
statick_tool/plugins/tool/perlcritic.py
statick_tool/plugins/tool/pycodestyle.py
alphatick-0.10.0.dist-info/LICENSE
alphatick-0.10.0.dist-info/METADATA
alphatick-0.10.0.dist-info/WHEEL
alphatick-0.10.0.dist-info/entry_points.txt
alphatick-0.10.0.dist-info/top_level.txt
alphatick-0.10.0.dist-info/RECORD
