Metadata-Version: 2.1
Name: alphatick
Version: 0.10.0
Summary: Making code quality easier.
Author: NIWC Pacific
License: CC0-1.0
Project-URL: Homepage, https://github.com/sscpac/statick
Project-URL: Bug Tracker, https://github.com/sscpac/statick/issues
Classifier: License :: CC0 1.0 Universal (CC0 1.0) Public Domain Dedication
Classifier: Programming Language :: Python :: 3
Classifier: Programming Language :: Python :: 3.8
Classifier: Programming Language :: Python :: 3.9
Classifier: Programming Language :: Python :: 3.10
Classifier: Programming Language :: Python :: 3.11
Classifier: Programming Language :: Python :: 3.12
Classifier: Topic :: Software Development :: Testing
Requires-Python: >=3.8
License-File: LICENSE
Requires-Dist: PyYAML
Requires-Dist: bandit
Requires-Dist: black
Requires-Dist: cmakelint
Requires-Dist: cpplint
Requires-Dist: docformatter
Requires-Dist: flawfinder
Requires-Dist: importlib-metadata
Requires-Dist: isort
Requires-Dist: lizard
Requires-Dist: mypy
Requires-Dist: pycodestyle
Requires-Dist: pydocstyle
Requires-Dist: pyflakes
Requires-Dist: pylint
Requires-Dist: ruff
Requires-Dist: tabulate
Requires-Dist: types-PyYAML
Requires-Dist: types-setuptools
Requires-Dist: types-tabulate
Requires-Dist: xmltodict
Requires-Dist: yamllint
Provides-Extra: dist
Requires-Dist: setuptools ; extra == 'dist'
Requires-Dist: wheel ; extra == 'dist'
Provides-Extra: docs
Requires-Dist: sphinx ==1.7.9 ; extra == 'docs'
Requires-Dist: yaml-1.3 ; extra == 'docs'
Requires-Dist: yapsy ; extra == 'docs'
Provides-Extra: test
Requires-Dist: flake8-pep3101 ; extra == 'test'
Requires-Dist: flake8 <5 ; extra == 'test'
Requires-Dist: lark ; extra == 'test'
Requires-Dist: mock ; extra == 'test'
Requires-Dist: pycodestyle ; extra == 'test'
Requires-Dist: pydocstyle ; extra == 'test'
Requires-Dist: pylint-django ; extra == 'test'
Requires-Dist: pytest ; extra == 'test'
Requires-Dist: pytest-cov ; extra == 'test'
Requires-Dist: pytest-flake8 ; extra == 'test'
Requires-Dist: pytest-isort ; extra == 'test'
Requires-Dist: tox ; extra == 'test'
Requires-Dist: tox-gh-actions ; extra == 'test'
